listhelpers/__init__.py
python_listhelpers-1.1.dist-info/DESCRIPTION.rst
python_listhelpers-1.1.dist-info/METADATA
python_listhelpers-1.1.dist-info/RECORD
python_listhelpers-1.1.dist-info/WHEEL
python_listhelpers-1.1.dist-info/metadata.json
python_listhelpers-1.1.dist-info/top_level.txt
