Metadata-Version: 2.0
Name: python-listhelpers
Version: 1.1
Summary: A set of various list helpers.
Home-page: https://github.com/ipsod/python_listhelpers
Author: Dusty Gamble
Author-email: dusty.gamble@gmail.com
License: MIT
Platform: UNKNOWN
Classifier: Topic :: Utilities
Classifier: Topic :: Text Processing
Classifier: Intended Audience :: Developers
Classifier: Operating System :: OS Independent
Classifier: Programming Language :: Python :: 2
Classifier: Programming Language :: Python :: 3
Classifier: License :: OSI Approved :: MIT License
